director/__init__.py
director/common.py
director/formats.py
director/formatters.py
director/identify.py
director/mocking.py
director_tester-0.0.1.dist-info/METADATA
director_tester-0.0.1.dist-info/WHEEL
director_tester-0.0.1.dist-info/top_level.txt
director_tester-0.0.1.dist-info/RECORD
