Metadata-Version: 2.1
Name: director-tester
Version: 0.0.1
Summary: Perform automated testing of Tkinter GUI applications
Home-page: UNKNOWN
Author: Brae Webb
Author-email: b.webb@uq.edu.au
License: MIT
Platform: UNKNOWN
Classifier: Programming Language :: Python :: 3
Classifier: Programming Language :: Python :: 3.9
Requires-Dist: behave
Requires-Dist: Pillow
